{
    "word_freq": [
        {
            "text": "MISS",
            "value": 1
        },
        {
            "text": "WILLOW",
            "value": 1
        },
        {
            "text": "GRACE",
            "value": 1
        },
        {
            "text": "LOVED",
            "value": 1
        },
        {
            "text": "CUDDLES",
            "value": 1
        },
        {
            "text": "AUNTY",
            "value": 1
        },
        {
            "text": "MADDIE",
            "value": 1
        },
        {
            "text": "RAINBOW",
            "value": 1
        },
        {
            "text": "LORIKEETS",
            "value": 1
        },
        {
            "text": "UNIVERSITY",
            "value": 1
        },
        {
            "text": "ADMINISTRATION",
            "value": 1
        },
        {
            "text": "MUTHAFUKIN",
            "value": 1
        }
    ]
}