{
    "word_freq": [
        {
            "text": "K",
            "value": 1
        },
        {
            "text": "muthafukin",
            "value": 1
        },
        {
            "text": "Amazing",
            "value": 1
        },
        {
            "text": "bread",
            "value": 1
        },
        {
            "text": "croissants",
            "value": 1
        },
        {
            "text": "breadclubofficial",
            "value": 1
        },
        {
            "text": "Like",
            "value": 1
        },
        {
            "text": "France",
            "value": 1
        },
        {
            "text": "Well",
            "value": 1
        },
        {
            "text": "done",
            "value": 1
        },
        {
            "text": "Brice",
            "value": 1
        },
        {
            "text": "et",
            "value": 1
        },
        {
            "text": "Tim",
            "value": 1
        },
        {
            "text": "good",
            "value": 2
        },
        {
            "text": "Bread",
            "value": 1
        },
        {
            "text": "Club",
            "value": 1
        },
        {
            "text": "posted",
            "value": 1
        },
        {
            "text": "photo",
            "value": 1
        },
        {
            "text": "Peter",
            "value": 1
        },
        {
            "text": "MacCallum",
            "value": 1
        },
        {
            "text": "Cancer",
            "value": 1
        },
        {
            "text": "Centre",
            "value": 1
        },
        {
            "text": "Joint",
            "value": 1
        },
        {
            "text": "statement",
            "value": 1
        },
        {
            "text": "Amplifies",
            "value": 1
        },
        {
            "text": "health",
            "value": 3
        },
        {
            "text": "issues",
            "value": 1
        },
        {
            "text": "impacts",
            "value": 1
        },
        {
            "text": "systems",
            "value": 1
        },
        {
            "text": "Climate",
            "value": 1
        },
        {
            "text": "change",
            "value": 1
        },
        {
            "text": "emergency",
            "value": 1
        },
        {
            "text": "Global",
            "value": 1
        },
        {
            "text": "temperatures",
            "value": 1
        },
        {
            "text": "increasing",
            "value": 1
        },
        {
            "text": "Bad",
            "value": 1
        },
        {
            "text": "Prof",
            "value": 2
        },
        {
            "text": "Eugenie",
            "value": 2
        },
        {
            "text": "Kayak",
            "value": 2
        },
        {
            "text": "Tracy",
            "value": 1
        },
        {
            "text": "Maund",
            "value": 1
        },
        {
            "text": "Oration",
            "value": 1
        },
        {
            "text": "opened",
            "value": 1
        },
        {
            "text": "Dr",
            "value": 2
        },
        {
            "text": "Vicki",
            "value": 1
        },
        {
            "text": "Woodward",
            "value": 1
        },
        {
            "text": "makes",
            "value": 1
        },
        {
            "text": "difference",
            "value": 2
        },
        {
            "text": "decide",
            "value": 1
        },
        {
            "text": "kind",
            "value": 1
        },
        {
            "text": "want",
            "value": 1
        },
        {
            "text": "make",
            "value": 2
        },
        {
            "text": "Jane",
            "value": 1
        },
        {
            "text": "Goodall",
            "value": 1
        },
        {
            "text": "Healthcare",
            "value": 1
        },
        {
            "text": "climate",
            "value": 1
        },
        {
            "text": "care",
            "value": 2
        },
        {
            "text": "laughing",
            "value": 1
        },
        {
            "text": "matter",
            "value": 1
        },
        {
            "text": "Teams",
            "value": 1
        },
        {
            "text": "hospitals",
            "value": 1
        },
        {
            "text": "work",
            "value": 1
        },
        {
            "text": "Executive",
            "value": 1
        },
        {
            "text": "team",
            "value": 1
        },
        {
            "text": "workshop",
            "value": 1
        },
        {
            "text": "today",
            "value": 1
        },
        {
            "text": "Translational",
            "value": 1
        },
        {
            "text": "Simulation",
            "value": 2
        },
        {
            "text": "Collaborative",
            "value": 1
        },
        {
            "text": "Gandel",
            "value": 1
        },
        {
            "text": "Service",
            "value": 1
        },
        {
            "text": "needed",
            "value": 1
        },
        {
            "text": "Shout",
            "value": 1
        },
        {
            "text": "marvellous",
            "value": 1
        },
        {
            "text": "staff",
            "value": 1
        },
        {
            "text": "wonderful",
            "value": 1
        },
        {
            "text": "I've",
            "value": 1
        },
        {
            "text": "lucky",
            "value": 1
        },
        {
            "text": "cared",
            "value": 1
        },
        {
            "text": "Melbourne",
            "value": 5
        },
        {
            "text": "world",
            "value": 1
        },
        {
            "text": "meeting",
            "value": 1
        },
        {
            "text": "finished",
            "value": 1
        },
        {
            "text": "early",
            "value": 1
        },
        {
            "text": "Allowing",
            "value": 1
        },
        {
            "text": "duck",
            "value": 1
        },
        {
            "text": "quick",
            "value": 1
        },
        {
            "text": "fix",
            "value": 1
        },
        {
            "text": "Spring",
            "value": 1
        },
        {
            "text": "finally",
            "value": 1
        },
        {
            "text": "asserting",
            "value": 1
        },
        {
            "text": "Royal",
            "value": 1
        },
        {
            "text": "Park",
            "value": 1
        },
        {
            "text": "Nature",
            "value": 1
        },
        {
            "text": "Playground",
            "value": 1
        },
        {
            "text": "Fleetwood",
            "value": 1
        },
        {
            "text": "Mac",
            "value": 1
        },
        {
            "text": "played",
            "value": 1
        },
        {
            "text": "orchestrally",
            "value": 1
        },
        {
            "text": "bet",
            "value": 1
        },
        {
            "text": "Hazy",
            "value": 1
        },
        {
            "text": "City",
            "value": 1
        }
    ]
}