{
    "count": 1,
    "data": [
        {
            "tid": 1576951244761047040,
            "uid": 60257801,
            "author": "Phillip Dowling",
            "time": "2022-10-03 15:04:09 +0000",
            "like_no": 0,
            "language": "en",
            "text": "Just posted a photo @ Port of Melbourne https://t.co/spr37345qt",
            "clean_text": "Just posted a photo Port of Melbourne",
            "place_name": "Melbourne, Victoria",
            "place_type": "city",
            "longitude": 144.9134231,
            "latitude": -37.81331,
            "photo_urls": []
        }
    ]
}