{
    "word_freq": [
        {
            "text": "Dan",
            "value": 1
        },
        {
            "text": "Andrews",
            "value": 1
        },
        {
            "text": "talking",
            "value": 1
        },
        {
            "text": "People",
            "value": 1
        },
        {
            "text": "ahead",
            "value": 1
        },
        {
            "text": "Profit",
            "value": 1
        },
        {
            "text": "needs",
            "value": 1
        },
        {
            "text": "apply",
            "value": 1
        },
        {
            "text": "across",
            "value": 1
        },
        {
            "text": "industries",
            "value": 1
        },
        {
            "text": "sectors",
            "value": 1
        },
        {
            "text": "communities",
            "value": 1
        },
        {
            "text": "areas",
            "value": 1
        },
        {
            "text": "Australia",
            "value": 3
        },
        {
            "text": "hospital",
            "value": 1
        },
        {
            "text": "system",
            "value": 2
        },
        {
            "text": "buckling",
            "value": 1
        },
        {
            "text": "weight",
            "value": 1
        },
        {
            "text": "presentstions",
            "value": 1
        },
        {
            "text": "Surely",
            "value": 1
        },
        {
            "text": "Bob",
            "value": 1
        },
        {
            "text": "donate",
            "value": 1
        },
        {
            "text": "funds",
            "value": 1
        },
        {
            "text": "businesses",
            "value": 1
        },
        {
            "text": "actual",
            "value": 1
        },
        {
            "text": "business",
            "value": 1
        },
        {
            "text": "helps",
            "value": 1
        },
        {
            "text": "actually",
            "value": 1
        },
        {
            "text": "keep",
            "value": 1
        },
        {
            "text": "sane",
            "value": 1
        },
        {
            "text": "enough",
            "value": 1
        },
        {
            "text": "continue",
            "value": 1
        },
        {
            "text": "life",
            "value": 1
        },
        {
            "text": "Dip",
            "value": 1
        },
        {
            "text": "books",
            "value": 1
        },
        {
            "text": "help",
            "value": 1
        },
        {
            "text": "Taking",
            "value": 1
        },
        {
            "text": "girl",
            "value": 1
        },
        {
            "text": "birthday",
            "value": 1
        },
        {
            "text": "dinner",
            "value": 1
        },
        {
            "text": "Cafe",
            "value": 1
        },
        {
            "text": "Rosco",
            "value": 1
        },
        {
            "text": "Chevron",
            "value": 1
        },
        {
            "text": "Melbourne",
            "value": 1
        },
        {
            "text": "Vic",
            "value": 1
        },
        {
            "text": "potential",
            "value": 1
        },
        {
            "text": "psychedelic",
            "value": 1
        },
        {
            "text": "compounds",
            "value": 1
        },
        {
            "text": "MDMA",
            "value": 1
        },
        {
            "text": "classic",
            "value": 1
        },
        {
            "text": "psychedelics",
            "value": 1
        },
        {
            "text": "including",
            "value": 2
        },
        {
            "text": "psilocybin",
            "value": 1
        },
        {
            "text": "treat",
            "value": 2
        },
        {
            "text": "mental",
            "value": 1
        },
        {
            "text": "health",
            "value": 1
        },
        {
            "text": "complications",
            "value": 1
        },
        {
            "text": "perhaps",
            "value": 1
        },
        {
            "text": "would",
            "value": 1
        },
        {
            "text": "lead",
            "value": 1
        },
        {
            "text": "entire",
            "value": 2
        },
        {
            "text": "framing",
            "value": 1
        },
        {
            "text": "drug",
            "value": 2
        },
        {
            "text": "use",
            "value": 1
        },
        {
            "text": "debate",
            "value": 1
        },
        {
            "text": "PTSD",
            "value": 2
        },
        {
            "text": "higher",
            "value": 1
        },
        {
            "text": "populations",
            "value": 1
        },
        {
            "text": "experienced",
            "value": 1
        },
        {
            "text": "physical",
            "value": 1
        },
        {
            "text": "violence",
            "value": 1
        },
        {
            "text": "sexual",
            "value": 1
        },
        {
            "text": "assault",
            "value": 1
        },
        {
            "text": "Medications",
            "value": 1
        },
        {
            "text": "cure",
            "value": 1
        },
        {
            "text": "trauma",
            "value": 4
        },
        {
            "text": "related",
            "value": 1
        },
        {
            "text": "psychotherapies",
            "value": 1
        },
        {
            "text": "Many",
            "value": 1
        },
        {
            "text": "therapists",
            "value": 1
        },
        {
            "text": "trained",
            "value": 1
        },
        {
            "text": "patients",
            "value": 1
        },
        {
            "text": "receiving",
            "value": 1
        },
        {
            "text": "evidence",
            "value": 1
        },
        {
            "text": "based",
            "value": 2
        },
        {
            "text": "care",
            "value": 1
        },
        {
            "text": "needed",
            "value": 1
        },
        {
            "text": "treatment",
            "value": 1
        },
        {
            "text": "within",
            "value": 1
        },
        {
            "text": "context",
            "value": 1
        },
        {
            "text": "treated",
            "value": 1
        },
        {
            "text": "dynamic",
            "value": 1
        },
        {
            "text": "way",
            "value": 1
        },
        {
            "text": "addressing",
            "value": 1
        },
        {
            "text": "traumatisation",
            "value": 1
        },
        {
            "text": "told",
            "value": 1
        },
        {
            "text": "detox",
            "value": 1
        },
        {
            "text": "access",
            "value": 1
        },
        {
            "text": "service",
            "value": 1
        },
        {
            "text": "unless",
            "value": 1
        },
        {
            "text": "went",
            "value": 1
        },
        {
            "text": "Opioid",
            "value": 1
        },
        {
            "text": "Replacement",
            "value": 1
        },
        {
            "text": "Therapy",
            "value": 1
        },
        {
            "text": "felt",
            "value": 1
        },
        {
            "text": "like",
            "value": 1
        },
        {
            "text": "coercion",
            "value": 1
        },
        {
            "text": "know",
            "value": 1
        },
        {
            "text": "Thought",
            "value": 1
        },
        {
            "text": "Leadership",
            "value": 1
        },
        {
            "text": "Event",
            "value": 1
        },
        {
            "text": "bringing",
            "value": 1
        },
        {
            "text": "people",
            "value": 1
        },
        {
            "text": "together",
            "value": 1
        },
        {
            "text": "similar",
            "value": 1
        },
        {
            "text": "values",
            "value": 1
        },
        {
            "text": "Podcast",
            "value": 1
        },
        {
            "text": "Producer",
            "value": 1
        },
        {
            "text": "Announcer",
            "value": 1
        },
        {
            "text": "internship",
            "value": 2
        },
        {
            "text": "available",
            "value": 2
        },
        {
            "text": "months",
            "value": 1
        },
        {
            "text": "Intern",
            "value": 1
        },
        {
            "text": "position",
            "value": 1
        },
        {
            "text": "Australian",
            "value": 1
        },
        {
            "text": "CPA",
            "value": 1
        },
        {
            "text": "accountant",
            "value": 1
        },
        {
            "text": "Please",
            "value": 1
        },
        {
            "text": "seek",
            "value": 1
        },
        {
            "text": "information",
            "value": 1
        },
        {
            "text": "day",
            "value": 1
        },
        {
            "text": "running",
            "value": 1
        },
        {
            "text": "rather",
            "value": 1
        },
        {
            "text": "large",
            "value": 1
        },
        {
            "text": "immunofluorescence",
            "value": 1
        },
        {
            "text": "stain",
            "value": 1
        },
        {
            "text": "study",
            "value": 1
        },
        {
            "text": "validate",
            "value": 1
        },
        {
            "text": "findings",
            "value": 1
        },
        {
            "text": "exciting",
            "value": 1
        },
        {
            "text": "single",
            "value": 1
        },
        {
            "text": "cell",
            "value": 1
        },
        {
            "text": "data",
            "value": 1
        },
        {
            "text": "wait",
            "value": 1
        },
        {
            "text": "see",
            "value": 2
        },
        {
            "text": "microscope",
            "value": 1
        },
        {
            "text": "flavors",
            "value": 1
        },
        {
            "text": "food",
            "value": 1
        },
        {
            "text": "Bali",
            "value": 2
        },
        {
            "text": "amazing",
            "value": 1
        }
    ]
}